{
  "title": "Gestione delle attività",
  "description": "Gestire e organizzare le attività",
  "create": "Nuova attività",
  "createDescription": "Inserisci le informazioni sulla nuova attività",
  "edit": "Modifica attività",
  "editButton": "Modifica",
  "editDescription": "Modifica le informazioni sull'attività",
  "delete": "Elimina",
  "deleteTitle": "Elimina attività",
  "subject": "Oggetto",
  "activityType": "Tipo di attività",
  "potentialCustomerId": "Potenziale cliente",
  "potentialCustomer": "cliente",
  "customer": "cliente",
  "selectCustomer": "Seleziona Cliente",
  "erpCustomerCode": "ERP Codice cliente",
  "product": "Stock/Prodotto",
  "selectProduct": "Seleziona Stock/Prodotto",
  "status": "Stato",
  "isCompleted": "completato",
  "priority": "priorità",
  "contactId": "Contatto",
  "contact": "persona",
  "assignedUserId": "Utente assegnato",
  "assignedUser": "Responsabile",
  "activityDate": "Data dell'attività",
  "activityDateRequired": "Data dell'attività richiesta",
  "createdDate": "Data di creazione",
  "updatedDate": "Data aggiornata",
  "actions": "Transazioni",
  "search": "Cerca",
  "filterByActivityType": "Filtra per tipo di attività",
  "filterByStatus": "Filtra per stato",
  "filterByPriority": "Filtra per priorità",
  "filterByPotentialCustomer": "Filtra per cliente",
  "filterByContact": "Filtra per persona",
  "filterByAssignedUser": "Filtra per utente assegnato",
  "filterByIsCompleted": "Filtra per stato di completamento",
  "filterByCreatedDateRange": "Filtra per intervallo di date di creazione",
  "noData": "Nessun dato trovato",
  "confirmDelete": "Sei sicuro di voler eliminare questa attività?",
  "createSuccess": "Attività creata con successo",
  "updateSuccess": "Attività aggiornata con successo",
  "deleteSuccess": "Attività eliminata correttamente",
  "createError": "Si è verificato un errore durante la creazione dell'attività",
  "updateError": "Si è verificato un errore durante l'aggiornamento dell'attività",
  "deleteError": "Si è verificato un errore durante l'eliminazione dell'attività",
  "subjectRequired": "L'argomento è obbligatorio",
  "subjectMaxLength": "L'oggetto può contenere fino a 100 caratteri",
  "descriptionMaxLength": "La descrizione può contenere fino a 500 caratteri",
  "activityTypeRequired": "È richiesta la selezione del tipo di attività",
  "activityTypeMaxLength": "Il tipo di attività può contenere un massimo di 50 caratteri",
  "statusRequired": "È richiesta la selezione dello stato",
  "statusMaxLength": "Lo stato può contenere fino a 50 caratteri",
  "priorityMaxLength": "La priorità può contenere fino a 50 caratteri",
  "enterSubject": "Inserisci l'oggetto",
  "enterDescription": "Inserisci la descrizione (facoltativo)",
  "selectActivityType": "Seleziona Tipo di attività",
  "selectPotentialCustomer": "Seleziona lead (facoltativo)",
  "enterErpCustomerCode": "ERP Inserisci il codice cliente (facoltativo)",
  "selectStatus": "Seleziona Stato",
  "selectPriority": "Seleziona priorità (facoltativo)",
  "selectContact": "Seleziona contatto (facoltativo)",
  "selectAssignedUser": "Seleziona utente assegnato (facoltativo)",
  "noCustomerSelected": "Cliente non selezionato",
  "noContactSelected": "Nessuna comunicazione selezionata",
  "noUserSelected": "Utente non selezionato",
  "noPrioritySelected": "Priorità non selezionata",
  "selectCustomerFirst": "Seleziona prima il cliente",
  "loading": "Caricamento...",
  "save": "Salva",
  "saving": "Registrazione...",
  "cancel": "Annulla",
  "previous": "Precedente",
  "next": "Avanti",
  "productDisplay": "{{code}} - {{name}}",
  "erpLabel": "ERP: {{code}}",
  "close": "Chiudi",
  "clearFilters": "Cancella filtri",
  "applyFilters": "Applica filtri",
  "markAsCompleted": "completo",
  "markAsInProgress": "Continua",
  "cancelActivity": "Annulla",
  "confirmMarkAsCompleted": "Sei sicuro di voler contrassegnare questa attività come completata?",
  "confirmMarkAsInProgress": "Sei sicuro di voler contrassegnare questa attività come in corso?",
  "confirmCancel": "Sei sicuro di voler annullare questa attività?",
  "markAsCompletedSuccess": "Attività contrassegnata come completata",
  "markAsInProgressSuccess": "Attività contrassegnata come in corso",
  "cancelSuccess": "L'attività è stata annullata",
  "statusChangeWarning": "Sei sicuro di voler modificare lo stato?",
  "autoCompleteStatus": "Verrà contrassegnato automaticamente quando lo stato è impostato su \"Completato\"",
  "activityTypeCall": "Cerca",
  "activityTypeMeeting": "incontro",
  "activityTypeEmail": "E-mail",
  "activityTypeTask": "Ricerca",
  "activityTypeNote": "nota",
  "activityTypeEvent": "evento",
  "statusScheduled": "pianificato",
  "statusInProgress": "In corso",
  "statusCompleted": "completato",
  "statusCanceled": "Annullato",
  "statusPostponed": "Rinviato",
  "priorityLow": "basso",
  "priorityMedium": "medio",
  "priorityHigh": "alto",
  "allActivityTypes": "Tutti i tipi di attività",
  "allStatuses": "Tutte le occasioni",
  "allPriorities": "Tutte le priorità",
  "completedActivities": "Attività completate",
  "pendingActivities": "Attività in sospeso",
  "highPriorityActivities": "Attività ad alta priorità",
  "noCompletedActivities": "Nessuna attività completata trovata",
  "noPendingActivities": "Nessuna attività in sospeso trovata",
  "activityDetails": "Dettagli attività",
  "customerInformation": "Informazioni sul cliente",
  "contactInformation": "Informazioni di contatto",
  "assignedUserInformation": "Informazioni sull'utente assegnato",
  "calendarView": "Visualizzazione calendario",
  "kanbanView": "Visualizzazione Kanban",
  "tableView": "Visualizzazione tabella",
  "switchToCalendar": "Passa alla visualizzazione calendario",
  "switchToKanban": "Passa alla visualizzazione Kanban",
  "switchToTable": "Passa alla visualizzazione tabella",
  "table": {
    "id": "ID",
    "subject": "Oggetto",
    "activityType": "Tipo di attività",
    "status": "Stato",
    "priority": "priorità",
    "potentialCustomer": "cliente",
    "contact": "persona",
    "assignedUser": "Responsabile",
    "isCompleted": "completato",
    "createdDate": "Data di creazione",
    "updatedDate": "Data aggiornata",
    "showing": "Mostrando {{from}}-{{to}} / {{total}}",
    "page": "Pagina {{current}} / {{total}}"
  },
  "advancedFilter": {
    "title": "Filtro avanzato",
    "add": "Aggiungi filtro",
    "column": "colonna",
    "operator": "operatore",
    "value": "Valore",
    "search": "Cerca",
    "clear": "chiaro",
    "remove": "Rimuovi",
    "equals": "è uguale",
    "contains": "Contiene",
    "startsWith": "Si inizia con",
    "endsWith": "termina con",
    "operatorEquals": "è uguale",
    "operatorContains": "Contiene",
    "operatorStartsWith": "Si inizia con",
    "operatorEndsWith": "termina con",
    "operator>": ">",
    "operator>=": ">=",
    "operator<": "<",
    "operator<=": "<=",
    "true": "Sì",
    "false": "no",
    "columnSubject": "Oggetto",
    "columnDescription": "Descrizione",
    "columnCustomerId": "Cliente No",
    "columnActivityTypeId": "Tipo di attività No",
    "columnPriority": "priorità",
    "columnDueDate": "Data di fine",
    "columnIsCompleted": "completato",
    "filterButton": "Filtro avanzato"
  },
  "columnCustomization": {
    "hiddenColumns": "Colonne nascoste",
    "visibleColumns": "Colonne da mostrare",
    "moveUp": "su",
    "moveDown": "giù"
  }
}
