{
  "title": "Cliente 360",
  "notFound": "Cliente non trovato",
  "error": "Si è verificato un errore",
  "retry": "Riprova",
  "currencyFilter": {
    "label": "valuta",
    "all": "Tutto"
  },
  "tabs": {
    "overview": "Riepilogo",
    "analytics": "analitica"
  },
  "kpi": {
    "totalDemands": "Offerta totale",
    "totalQuotations": "Offerta totale",
    "totalOrders": "Ordine totale",
    "openQuotations": "Offerta aperta",
    "openOrders": "Ordine in sospeso"
  },
  "sections": {
    "contacts": "Comunicazioni",
    "shippingAddresses": "Indirizzi di spedizione",
    "recentDemands": "Ultime offerte",
    "recentQuotations": "Ultime offerte",
    "recentOrders": "Ultimi ordini",
    "recentActivities": "Ultime attività",
    "timeline": "Cronologia"
  },
  "analytics": {
    "error": "Impossibile caricare i dati di analisi",
    "last12MonthsOrderAmount": "Importo dell'ordine degli ultimi 12 mesi",
    "openQuotationAmount": "Importo dell'offerta aperta",
    "openOrderAmount": "Importo dell'ordine aperto",
    "activityCount": "Numero di attività",
    "lastActivityDate": "Data dell'ultima attività"
  },
  "analyticsCharts": {
    "demand": "Offerta",
    "quotation": "Offerta",
    "order": "Ordine",
    "last12MonthsOrderAmount": "Ordine degli ultimi 12 mesi",
    "openQuotationAmount": "Offerta aperta",
    "openOrderAmount": "Ordine aperto",
    "distributionTitle": "distribuzione",
    "monthlyTrendTitle": "Tendenza mensile",
    "amountComparisonTitle": "Confronto importi"
  },
  "currencyTotals": {
    "currency": "Valuta",
    "demandAmount": "Importo dell'offerta",
    "quotationAmount": "Importo dell'offerta",
    "orderAmount": "Importo dell'ordine"
  },
  "revenueQuality": {
    "title": "Qualità dei ricavi",
    "churnRisk": "Rischio di perdita",
    "upsell": "Tendenza all'upselling",
    "payment": "Comportamento nei pagamenti",
    "segment": "Segmento RFM",
    "ltv": "LTV"
  },
  "cohort": {
    "title": "Mantenere una coorte",
    "empty": "Nessun dato di coorte",
    "cohortKey": "coorte"
  },
  "actions": {
    "title": "Azioni consigliate",
    "empty": "Nessuna azione consigliata",
    "execute": "Applicare"
  },
  "status": {}
}
